README.txt
setup.py
gabicalculator/__init__.py
gabicalculator/fibo.py
gabicalculator.egg-info/PKG-INFO
gabicalculator.egg-info/SOURCES.txt
gabicalculator.egg-info/dependency_links.txt
gabicalculator.egg-info/top_level.txt